LICENSE
MANIFEST.in
README.md
pytest.ini
requirements.txt
setup.py
docs/jel-logo.png
jel/__init__.py
jel/collect_entity_data.py
jel/common_config.py
jel/file_cache.py
jel/kb.py
jel/mention_predictor.py
jel/prior_dict_creator.py
jel.egg-info/PKG-INFO
jel.egg-info/SOURCES.txt
jel.egg-info/dependency_links.txt
jel.egg-info/requires.txt
jel.egg-info/top_level.txt
jel/biencoder/__init__.py
jel/biencoder/dataset_reader.py
jel/biencoder/encoder.py
jel/biencoder/model.py
jel/biencoder/parameters.py
jel/biencoder/predictor.py
jel/biencoder/train.py
jel/biencoder/utils.py
jel/utils/__init__.py
jel/utils/common.py
jel/utils/embedder.py
jel/utils/tokenizer.py
scripts/biencoder_training_check.py
scripts/small_dataset_creator.py
scripts/sudachi_preprocess.py
tests/README.md
tests/__init__.py
tests/biencoder/__init__.py
tests/biencoder/test_predictor.py
tests/biencoder/test_train.py
tests/utils/__init__.py
tests/utils/test_common.py
tests/utils/test_tokenizer.py