Metadata-Version: 2.1
Name: jel
Version: 0.1.3
Summary: Japanese Entity Linker.
Home-page: https://github.com/izuna385/jel
Author: izuna385
Author-email: izuna385@gmail.com
License: UNKNOWN
Keywords: jel
Platform: UNKNOWN
Classifier: Development Status :: 2 - Pre-Alpha
Classifier: Natural Language :: English
Classifier: License :: OSI Approved :: Apache Software License
Classifier: Programming Language :: Python :: 3.7
Classifier: Operating System :: OS Independent
